tests/__init__.py
tests/test_tmldabao.py
tmldabao-0.0.1.dist-info/LICENSE
tmldabao-0.0.1.dist-info/METADATA
tmldabao-0.0.1.dist-info/WHEEL
tmldabao-0.0.1.dist-info/top_level.txt
tmldabao-0.0.1.dist-info/RECORD
