Metadata-Version: 2.1
Name: tmldabao
Version: 0.0.1
Summary: A small example package
Home-page: https://github.com/tmldabao/tmldabao
Author: tml
Author-email: qq@qq.com
Classifier: Programming Language :: Python :: 3
Classifier: License :: OSI Approved :: MIT License
Classifier: Operating System :: OS Independent
Requires-Python: >=3.1
License-File: LICENSE
Requires-Dist: pandas >=1.0.3
